{
  "script_id": 31,
  "start_page": 76771,
  "end_page": 79329,
  "total_pages": 2559,
  "estimated_results": 255900,
  "current_page": 76771,
  "total_files_downloaded": 50,
  "start_time": "2025-11-11T07:23:03.282274",
  "last_updated": "2025-11-11T07:32:03.130430",
  "status": "not_started",
  "pages_completed": [],
  "failed_downloads": [],
  "yearly_counts": {
    "2025": 50
  },
  "downloaded_files": [
    {
      "success": true,
      "filename": "CRM(M)_1737_2025_of_PRAMATHA_DAS_AND_ANR._Vs_STATE_OF_WEST_BENGAL_CNR_WBCHCA0450182025_1762845787424.pdf",
      "s3_key": "judgments/CRM(M)_1737_2025_of_PRAMATHA_DAS_AND_ANR._Vs_STATE_OF_WEST_BENGAL_CNR_WBCHCA0450182025_1762845787424_31.pdf",
      "uploaded_to_s3": true,
      "cnr": "WBCHCA0450182025",
      "case_title": "CRM(M)/1737/2025 of PRAMATHA DAS AND ANR. Vs STATE OF WEST BENGAL",
      "decision_date": "10-11-2025",
      "decision_year": 2025,
      "download_time": "2025-11-11T07:23:24.263336",
      "download_duration_seconds": 7.44
    },
    {
      "success": true,
      "filename": "CR._APP_(SJ)_2324_2024_of_Jivit_Paswan_Vs_The_State_of_Bihar_CNR_BRHC010476522024_1762845787478.pdf",
      "s3_key": "judgments/CR._APP_(SJ)_2324_2024_of_Jivit_Paswan_Vs_The_State_of_Bihar_CNR_BRHC010476522024_1762845787478_31.pdf",
      "uploaded_to_s3": true,
      "cnr": "BRHC010476522024",
      "case_title": "CR. APP (SJ)/2324/2024 of Jivit Paswan Vs The State of Bihar",
      "decision_date": "10-11-2025",
      "decision_year": 2025,
      "download_time": "2025-11-11T07:23:33.972097",
      "download_duration_seconds": 7.13
    },
    {
      "success": true,
      "filename": "CR._MISC._45204_2025_of_Yash_Kumar_Gupta_Vs_The_State_of_Bihar_CNR_BRHC010639342025_1762845787547.pdf",
      "s3_key": "judgments/CR._MISC._45204_2025_of_Yash_Kumar_Gupta_Vs_The_State_of_Bihar_CNR_BRHC010639342025_1762845787547_31.pdf",
      "uploaded_to_s3": true,
      "cnr": "BRHC010639342025",
      "case_title": "CR. MISC./45204/2025 of Yash Kumar Gupta Vs The State of Bihar",
      "decision_date": "10-11-2025",
      "decision_year": 2025,
      "download_time": "2025-11-11T07:23:44.409262",
      "download_duration_seconds": 7.86
    },
    {
      "success": true,
      "filename": "CR._MISC._74430_2025_of_Raushan_Raj_@_Raushan_Jaiswal_Vs_The_State_of_Bihar_CNR_BRHC011079252025_1762845787622.pdf",
      "s3_key": "judgments/CR._MISC._74430_2025_of_Raushan_Raj_@_Raushan_Jaiswal_Vs_The_State_of_Bihar_CNR_BRHC011079252025_1762845787622_31.pdf",
      "uploaded_to_s3": true,
      "cnr": "BRHC011079252025",
      "case_title": "CR. MISC./74430/2025 of Raushan Raj @ Raushan Jaiswal Vs The State of Bihar",
      "decision_date": "10-11-2025",
      "decision_year": 2025,
      "download_time": "2025-11-11T07:23:54.361819",
      "download_duration_seconds": 7.31
    },
    {
      "success": true,
      "filename": "CR.RA_926_2023_of_HEMENDRABHAI_MAHASUKHLAL_SHAH_Vs_STATE_OF_GUJARAT_CNR_GJHC240447252023_1762845787678.pdf",
      "s3_key": "judgments/CR.RA_926_2023_of_HEMENDRABHAI_MAHASUKHLAL_SHAH_Vs_STATE_OF_GUJARAT_CNR_GJHC240447252023_1762845787678_31.pdf",
      "uploaded_to_s3": true,
      "cnr": "GJHC240447252023",
      "case_title": "CR.RA/926/2023 of HEMENDRABHAI MAHASUKHLAL SHAH Vs STATE OF GUJARAT",
      "decision_date": "10-11-2025",
      "decision_year": 2025,
      "download_time": "2025-11-11T07:24:04.139550",
      "download_duration_seconds": 7.2
    },
    {
      "success": true,
      "filename": "CMP_1572_2025_of_PUNYAPRAVA_DAS_Vs_MITALI_DAS_@_MOHANTY_CNR_ODHC010674702025_1762845787747.pdf",
      "s3_key": "judgments/CMP_1572_2025_of_PUNYAPRAVA_DAS_Vs_MITALI_DAS_@_MOHANTY_CNR_ODHC010674702025_1762845787747_31.pdf",
      "uploaded_to_s3": true,
      "cnr": "ODHC010674702025",
      "case_title": "CMP/1572/2025 of PUNYAPRAVA DAS Vs MITALI DAS @ MOHANTY",
      "decision_date": "10-11-2025",
      "decision_year": 2025,
      "download_time": "2025-11-11T07:24:14.307312",
      "download_duration_seconds": 7.59
    },
    {
      "success": true,
      "filename": "WP(C)_30750_2025_of_DEEPAK_KUMAR_OJHA_Vs_STATE_OF_ODISHA_CNR_ODHC010772592025_1762845787802.pdf",
      "s3_key": "judgments/WP(C)_30750_2025_of_DEEPAK_KUMAR_OJHA_Vs_STATE_OF_ODISHA_CNR_ODHC010772592025_1762845787802_31.pdf",
      "uploaded_to_s3": true,
      "cnr": "ODHC010772592025",
      "case_title": "WP(C)/30750/2025 of DEEPAK KUMAR OJHA Vs STATE OF ODISHA",
      "decision_date": "10-11-2025",
      "decision_year": 2025,
      "download_time": "2025-11-11T07:24:24.557210",
      "download_duration_seconds": 7.62
    },
    {
      "success": true,
      "filename": "ABLAPL_10532_2025_of_SNIGDHA_DAS_Vs_STATE_OF_ODISHA_CNR_ODHC010620992025_1762845787867.pdf",
      "s3_key": "judgments/ABLAPL_10532_2025_of_SNIGDHA_DAS_Vs_STATE_OF_ODISHA_CNR_ODHC010620992025_1762845787867_31.pdf",
      "uploaded_to_s3": true,
      "cnr": "ODHC010620992025",
      "case_title": "ABLAPL/10532/2025 of SNIGDHA DAS Vs STATE OF ODISHA",
      "decision_date": "10-11-2025",
      "decision_year": 2025,
      "download_time": "2025-11-11T07:24:34.706051",
      "download_duration_seconds": 7.56
    },
    {
      "success": true,
      "filename": "CCP_633_2023_of_SMT._PRAMILA_MONGIA_W_O_SHRI_BHUVANESH_KUMAR_MONGIA,_Vs_SHRI_NAVEEN_JAIN_(I.A.S.)_SECRETARY_TO_THE_GOVERNMENT_OF_RAJASTHAN_CNR_RJHC020446872023_1762845787921.pdf",
      "s3_key": "judgments/CCP_633_2023_of_SMT._PRAMILA_MONGIA_W_O_SHRI_BHUVANESH_KUMAR_MONGIA,_Vs_SHRI_NAVEEN_JAIN_(I.A.S.)_SECRETARY_TO_THE_GOVERNMENT_OF_RAJASTHAN_CNR_RJHC020446872023_1762845787921_31.pdf",
      "uploaded_to_s3": true,
      "cnr": "RJHC020446872023",
      "case_title": "CCP/633/2023 of SMT. PRAMILA MONGIA W/O SHRI BHUVANESH KUMAR MONGIA, Vs SHRI NAVEEN JAIN (I.A.S.) SECRETARY TO THE GOVERNMENT OF RAJASTHAN.",
      "decision_date": "10-11-2025",
      "decision_year": 2025,
      "download_time": "2025-11-11T07:24:44.767154",
      "download_duration_seconds": 7.47
    },
    {
      "success": true,
      "filename": "WPA_722_2024_of_SANJIT_CHAKRABORTY_AND_ANR_Vs_PANIHATI_MUNICIPALITY_AND_ORS_CNR_WBCHCA0014312024_1762845787977.pdf",
      "s3_key": "judgments/WPA_722_2024_of_SANJIT_CHAKRABORTY_AND_ANR_Vs_PANIHATI_MUNICIPALITY_AND_ORS_CNR_WBCHCA0014312024_1762845787977_31.pdf",
      "uploaded_to_s3": true,
      "cnr": "WBCHCA0014312024",
      "case_title": "WPA/722/2024 of SANJIT CHAKRABORTY AND ANR Vs PANIHATI MUNICIPALITY AND ORS",
      "decision_date": "10-11-2025",
      "decision_year": 2025,
      "download_time": "2025-11-11T07:24:54.525332",
      "download_duration_seconds": 7.07
    },
    {
      "success": true,
      "filename": "WPA_1636_2025_of_R.B._CONSTRUCTION_REPRESENTED_BY_ITS_PROPRIETOR_RANENDU_BISWAS_Vs_STATE_OF_WEST_BENGAL_AND_ORS_CNR_WBCHCA0030562025_1762845788034.pdf",
      "s3_key": "judgments/WPA_1636_2025_of_R.B._CONSTRUCTION_REPRESENTED_BY_ITS_PROPRIETOR_RANENDU_BISWAS_Vs_STATE_OF_WEST_BENGAL_AND_ORS_CNR_WBCHCA0030562025_1762845788034_31.pdf",
      "uploaded_to_s3": true,
      "cnr": "WBCHCA0030562025",
      "case_title": "WPA/1636/2025 of R.B. CONSTRUCTION REPRESENTED BY ITS PROPRIETOR RANENDU BISWAS Vs STATE OF WEST BENGAL AND ORS.",
      "decision_date": "10-11-2025",
      "decision_year": 2025,
      "download_time": "2025-11-11T07:25:04.243885",
      "download_duration_seconds": 7.14
    },
    {
      "success": true,
      "filename": "WPA_18785_2025_of_INFAUL_KARIM_Vs_STATE_OF_WEST_BENGAL_AND_ORS_CNR_WBCHCA0382622025_1762845788118.pdf",
      "s3_key": "judgments/WPA_18785_2025_of_INFAUL_KARIM_Vs_STATE_OF_WEST_BENGAL_AND_ORS_CNR_WBCHCA0382622025_1762845788118_31.pdf",
      "uploaded_to_s3": true,
      "cnr": "WBCHCA0382622025",
      "case_title": "WPA/18785/2025 of INFAUL KARIM Vs STATE OF WEST BENGAL AND ORS.",
      "decision_date": "10-11-2025",
      "decision_year": 2025,
      "download_time": "2025-11-11T07:25:14.310231",
      "download_duration_seconds": 7.48
    },
    {
      "success": true,
      "filename": "CRM(M)_1585_2025_of_BADAL_DAS_Vs_STATE_OF_WEST_BENGAL_CNR_WBCHCA0421602025_1762845788179.pdf",
      "s3_key": "judgments/CRM(M)_1585_2025_of_BADAL_DAS_Vs_STATE_OF_WEST_BENGAL_CNR_WBCHCA0421602025_1762845788179_31.pdf",
      "uploaded_to_s3": true,
      "cnr": "WBCHCA0421602025",
      "case_title": "CRM(M)/1585/2025 of BADAL DAS Vs STATE OF WEST BENGAL",
      "decision_date": "10-11-2025",
      "decision_year": 2025,
      "download_time": "2025-11-11T07:25:25.024374",
      "download_duration_seconds": 8.14
    },
    {
      "success": true,
      "filename": "CR._MISC._74535_2025_of_Pritam_Kumar_@_Sonu_Vs_The_State_of_Bihar_CNR_BRHC011082372025_1762845788241.pdf",
      "s3_key": "judgments/CR._MISC._74535_2025_of_Pritam_Kumar_@_Sonu_Vs_The_State_of_Bihar_CNR_BRHC011082372025_1762845788241_31.pdf",
      "uploaded_to_s3": true,
      "cnr": "BRHC011082372025",
      "case_title": "CR. MISC./74535/2025 of Pritam Kumar @ Sonu Vs The State of Bihar",
      "decision_date": "10-11-2025",
      "decision_year": 2025,
      "download_time": "2025-11-11T07:25:34.703392",
      "download_duration_seconds": 7.07
    },
    {
      "success": true,
      "filename": "CR._MISC._74545_2025_of_Anil_Kumar_Vs_The_State_of_Bihar_CNR_BRHC011061412025_1762845788293.pdf",
      "s3_key": "judgments/CR._MISC._74545_2025_of_Anil_Kumar_Vs_The_State_of_Bihar_CNR_BRHC011061412025_1762845788293_31.pdf",
      "uploaded_to_s3": true,
      "cnr": "BRHC011061412025",
      "case_title": "CR. MISC./74545/2025 of Anil Kumar Vs The State of Bihar",
      "decision_date": "10-11-2025",
      "decision_year": 2025,
      "download_time": "2025-11-11T07:25:44.372570",
      "download_duration_seconds": 7.07
    },
    {
      "success": true,
      "filename": "CR._MISC._62442_2025_of_Chutoon_Bhagat_@_Chutoon_Kumar_Vs_The_State_of_Bihar_CNR_BRHC010865522025_1762845788350.pdf",
      "s3_key": "judgments/CR._MISC._62442_2025_of_Chutoon_Bhagat_@_Chutoon_Kumar_Vs_The_State_of_Bihar_CNR_BRHC010865522025_1762845788350_31.pdf",
      "uploaded_to_s3": true,
      "cnr": "BRHC010865522025",
      "case_title": "CR. MISC./62442/2025 of Chutoon Bhagat @ Chutoon Kumar Vs The State of Bihar",
      "decision_date": "10-11-2025",
      "decision_year": 2025,
      "download_time": "2025-11-11T07:25:54.029974",
      "download_duration_seconds": 7.07
    },
    {
      "success": true,
      "filename": "CR._MISC._74509_2025_of_Vinod_Paswan_Vs_The_State_of_Bihar_CNR_BRHC010990602025_1762845788406.pdf",
      "s3_key": "judgments/CR._MISC._74509_2025_of_Vinod_Paswan_Vs_The_State_of_Bihar_CNR_BRHC010990602025_1762845788406_31.pdf",
      "uploaded_to_s3": true,
      "cnr": "BRHC010990602025",
      "case_title": "CR. MISC./74509/2025 of Vinod Paswan Vs The State of Bihar",
      "decision_date": "10-11-2025",
      "decision_year": 2025,
      "download_time": "2025-11-11T07:26:03.787085",
      "download_duration_seconds": 7.18
    },
    {
      "success": true,
      "filename": "CR._MISC._71264_2025_of_BHAWANI_SAH_@_SANTOSH_SAH_@_BHAWANI_NANDAN_SAH_Vs_The_State_of_Bihar_CNR_BRHC010834292025_1762845788462.pdf",
      "s3_key": "judgments/CR._MISC._71264_2025_of_BHAWANI_SAH_@_SANTOSH_SAH_@_BHAWANI_NANDAN_SAH_Vs_The_State_of_Bihar_CNR_BRHC010834292025_1762845788462_31.pdf",
      "uploaded_to_s3": true,
      "cnr": "BRHC010834292025",
      "case_title": "CR. MISC./71264/2025 of BHAWANI SAH @ SANTOSH SAH @ BHAWANI NANDAN SAH Vs The State of Bihar",
      "decision_date": "10-11-2025",
      "decision_year": 2025,
      "download_time": "2025-11-11T07:26:13.419993",
      "download_duration_seconds": 7.04
    },
    {
      "success": true,
      "filename": "CR._MISC._74534_2025_of_Ravindra_Singh_@_Ravindra_Kumar_Singh_Vs_The_State_of_Bihar_CNR_BRHC011058582025_1762845788543.pdf",
      "s3_key": "judgments/CR._MISC._74534_2025_of_Ravindra_Singh_@_Ravindra_Kumar_Singh_Vs_The_State_of_Bihar_CNR_BRHC011058582025_1762845788543_31.pdf",
      "uploaded_to_s3": true,
      "cnr": "BRHC011058582025",
      "case_title": "CR. MISC./74534/2025 of Ravindra Singh @ Ravindra Kumar Singh Vs The State of Bihar",
      "decision_date": "10-11-2025",
      "decision_year": 2025,
      "download_time": "2025-11-11T07:26:23.178210",
      "download_duration_seconds": 7.15
    },
    {
      "success": true,
      "filename": "CR._MISC._74268_2025_of_Niranjan_Kumar_Vs_The_State_of_Bihar_CNR_BRHC011065622025_1762845788600.pdf",
      "s3_key": "judgments/CR._MISC._74268_2025_of_Niranjan_Kumar_Vs_The_State_of_Bihar_CNR_BRHC011065622025_1762845788600_31.pdf",
      "uploaded_to_s3": true,
      "cnr": "BRHC011065622025",
      "case_title": "CR. MISC./74268/2025 of Niranjan Kumar Vs The State of Bihar",
      "decision_date": "10-11-2025",
      "decision_year": 2025,
      "download_time": "2025-11-11T07:26:33.051568",
      "download_duration_seconds": 7.09
    },
    {
      "success": true,
      "filename": "CR._MISC._71637_2025_of_Nitish_Bind_Vs_The_State_of_Bihar_CNR_BRHC011043122025_1762845788658.pdf",
      "s3_key": "judgments/CR._MISC._71637_2025_of_Nitish_Bind_Vs_The_State_of_Bihar_CNR_BRHC011043122025_1762845788658_31.pdf",
      "uploaded_to_s3": true,
      "cnr": "BRHC011043122025",
      "case_title": "CR. MISC./71637/2025 of Nitish Bind Vs The State of Bihar",
      "decision_date": "10-11-2025",
      "decision_year": 2025,
      "download_time": "2025-11-11T07:26:42.851259",
      "download_duration_seconds": 7.2
    },
    {
      "success": true,
      "filename": "CR._MISC._44606_2025_of_Sandeep_Kumar_Vs_The_State_of_Bihar_CNR_BRHC010619802025_1762845788706.pdf",
      "s3_key": "judgments/CR._MISC._44606_2025_of_Sandeep_Kumar_Vs_The_State_of_Bihar_CNR_BRHC010619802025_1762845788706_31.pdf",
      "uploaded_to_s3": true,
      "cnr": "BRHC010619802025",
      "case_title": "CR. MISC./44606/2025 of Sandeep Kumar Vs The State of Bihar",
      "decision_date": "10-11-2025",
      "decision_year": 2025,
      "download_time": "2025-11-11T07:26:52.833609",
      "download_duration_seconds": 7.38
    },
    {
      "success": true,
      "filename": "CR._MISC._75420_2025_of_Ritesh_Kumar_@_Ritesh_Singh_Vs_The_State_of_Bihar_CNR_BRHC011086372025_1762845788761.pdf",
      "s3_key": "judgments/CR._MISC._75420_2025_of_Ritesh_Kumar_@_Ritesh_Singh_Vs_The_State_of_Bihar_CNR_BRHC011086372025_1762845788761_31.pdf",
      "uploaded_to_s3": true,
      "cnr": "BRHC011086372025",
      "case_title": "CR. MISC./75420/2025 of Ritesh Kumar @ Ritesh Singh Vs The State of Bihar",
      "decision_date": "10-11-2025",
      "decision_year": 2025,
      "download_time": "2025-11-11T07:27:02.761657",
      "download_duration_seconds": 7.25
    },
    {
      "success": true,
      "filename": "SCA_9032_2025_of_JHA_PREMSHEEL_NANDKISHOR_Vs_MANAGING_TRUSTEE,_BABA_RAGHUNATHDASJI_EDUCATION_TRUST_CNR_GJHC240469322025_1762845788824.pdf",
      "s3_key": "judgments/SCA_9032_2025_of_JHA_PREMSHEEL_NANDKISHOR_Vs_MANAGING_TRUSTEE,_BABA_RAGHUNATHDASJI_EDUCATION_TRUST_CNR_GJHC240469322025_1762845788824_31.pdf",
      "uploaded_to_s3": true,
      "cnr": "GJHC240469322025",
      "case_title": "SCA/9032/2025 of JHA PREMSHEEL NANDKISHOR Vs MANAGING TRUSTEE, BABA RAGHUNATHDASJI EDUCATION TRUST",
      "decision_date": "10-11-2025",
      "decision_year": 2025,
      "download_time": "2025-11-11T07:27:12.499532",
      "download_duration_seconds": 7.13
    },
    {
      "success": true,
      "filename": "SCR.A_14556_2025_of_AKIL_@_GABHARU_SALIMBHAI_@_HANIFBHAI_SUMRA_Vs_STATE_OF_GUJARAT_CNR_GJHC240776712025_1762845788931.pdf",
      "s3_key": "judgments/SCR.A_14556_2025_of_AKIL_@_GABHARU_SALIMBHAI_@_HANIFBHAI_SUMRA_Vs_STATE_OF_GUJARAT_CNR_GJHC240776712025_1762845788931_31.pdf",
      "uploaded_to_s3": true,
      "cnr": "GJHC240776712025",
      "case_title": "SCR.A/14556/2025 of AKIL @ GABHARU SALIMBHAI @ HANIFBHAI SUMRA Vs STATE OF GUJARAT",
      "decision_date": "10-11-2025",
      "decision_year": 2025,
      "download_time": "2025-11-11T07:27:22.906731",
      "download_duration_seconds": 7.82
    },
    {
      "success": true,
      "filename": "CMP_1761_2025_of_GAYADHAR_MALIK_Vs_JAMBU_MALIK_CNR_ODHC010767172025_1762846072080.pdf",
      "s3_key": "judgments/CMP_1761_2025_of_GAYADHAR_MALIK_Vs_JAMBU_MALIK_CNR_ODHC010767172025_1762846072080_31.pdf",
      "uploaded_to_s3": true,
      "cnr": "ODHC010767172025",
      "case_title": "CMP/1761/2025 of GAYADHAR MALIK Vs JAMBU MALIK",
      "decision_date": "10-11-2025",
      "decision_year": 2025,
      "download_time": "2025-11-11T07:28:06.627602",
      "download_duration_seconds": 7.54
    },
    {
      "success": true,
      "filename": "CA_107_2023_of_RAJU_PANDURANG_SONAR_Vs_SHUBH_NIRBHAY_MAJHI_AND_ANR_CNR_HCBM050007042022_1762846072124.pdf",
      "s3_key": "judgments/CA_107_2023_of_RAJU_PANDURANG_SONAR_Vs_SHUBH_NIRBHAY_MAJHI_AND_ANR_CNR_HCBM050007042022_1762846072124_31.pdf",
      "uploaded_to_s3": true,
      "cnr": "HCBM050007042022",
      "case_title": "CA/107/2023 of RAJU PANDURANG SONAR Vs SHUBH NIRBHAY MAJHI AND ANR",
      "decision_date": "10-11-2025",
      "decision_year": 2025,
      "download_time": "2025-11-11T07:28:16.219887",
      "download_duration_seconds": 7.0
    },
    {
      "success": true,
      "filename": "C528_1899_2025_of_BHOOP_RAM_Vs_STATE_OF_UTTARAKHAND_CNR_UKHC010167242025_1762846072207.pdf",
      "s3_key": "judgments/C528_1899_2025_of_BHOOP_RAM_Vs_STATE_OF_UTTARAKHAND_CNR_UKHC010167242025_1762846072207_31.pdf",
      "uploaded_to_s3": true,
      "cnr": "UKHC010167242025",
      "case_title": "C528/1899/2025 of BHOOP RAM Vs STATE OF UTTARAKHAND",
      "decision_date": "10-11-2025",
      "decision_year": 2025,
      "download_time": "2025-11-11T07:28:25.857024",
      "download_duration_seconds": 7.01
    },
    {
      "success": true,
      "filename": "BLAPL_8594_2025_of_JOHAN_MAJHI_Vs_STATE_OF_ODISHA_CNR_ODHC010572312025_1762846072258.pdf",
      "s3_key": "judgments/BLAPL_8594_2025_of_JOHAN_MAJHI_Vs_STATE_OF_ODISHA_CNR_ODHC010572312025_1762846072258_31.pdf",
      "uploaded_to_s3": true,
      "cnr": "ODHC010572312025",
      "case_title": "BLAPL/8594/2025 of JOHAN MAJHI Vs STATE OF ODISHA",
      "decision_date": "10-11-2025",
      "decision_year": 2025,
      "download_time": "2025-11-11T07:28:35.989125",
      "download_duration_seconds": 7.48
    },
    {
      "success": true,
      "filename": "COCP_120_2018_of_RESHAM_SINGH_Vs_B_S_SANDHU_CNR_PHHC010006622018_1762846072302.pdf",
      "s3_key": "judgments/COCP_120_2018_of_RESHAM_SINGH_Vs_B_S_SANDHU_CNR_PHHC010006622018_1762846072302_31.pdf",
      "uploaded_to_s3": true,
      "cnr": "PHHC010006622018",
      "case_title": "COCP/120/2018 of RESHAM SINGH Vs B S SANDHU",
      "decision_date": "10-11-2025",
      "decision_year": 2025,
      "download_time": "2025-11-11T07:28:45.901603",
      "download_duration_seconds": 7.3
    },
    {
      "success": true,
      "filename": "MFA_10459_2018_of_JAVARAMMA_Vs_THE_SPECIAL_LAND_ACQUISITION_OFFICER_CNR_KAHC010301392018_1762846072349.pdf",
      "s3_key": "judgments/MFA_10459_2018_of_JAVARAMMA_Vs_THE_SPECIAL_LAND_ACQUISITION_OFFICER_CNR_KAHC010301392018_1762846072349_31.pdf",
      "uploaded_to_s3": true,
      "cnr": "KAHC010301392018",
      "case_title": "MFA/10459/2018 of JAVARAMMA Vs THE SPECIAL LAND ACQUISITION OFFICER",
      "decision_date": "10-11-2025",
      "decision_year": 2025,
      "download_time": "2025-11-11T07:28:55.249325",
      "download_duration_seconds": 6.76
    },
    {
      "success": true,
      "filename": "CR._MISC._75519_2025_of_Mathura_Chaudhary_@_Jitendra_Singh_Vs_The_State_of_Bihar_CNR_BRHC011101912025_1762846072401.pdf",
      "s3_key": "judgments/CR._MISC._75519_2025_of_Mathura_Chaudhary_@_Jitendra_Singh_Vs_The_State_of_Bihar_CNR_BRHC011101912025_1762846072401_31.pdf",
      "uploaded_to_s3": true,
      "cnr": "BRHC011101912025",
      "case_title": "CR. MISC./75519/2025 of Mathura Chaudhary @ Jitendra Singh Vs The State of Bihar",
      "decision_date": "10-11-2025",
      "decision_year": 2025,
      "download_time": "2025-11-11T07:29:05.040371",
      "download_duration_seconds": 7.19
    },
    {
      "success": true,
      "filename": "CR._MISC._74818_2025_of_Sumit_Kumar_Vs_The_State_of_Bihar_CNR_BRHC011099312025_1762846072454.pdf",
      "s3_key": "judgments/CR._MISC._74818_2025_of_Sumit_Kumar_Vs_The_State_of_Bihar_CNR_BRHC011099312025_1762846072454_31.pdf",
      "uploaded_to_s3": true,
      "cnr": "BRHC011099312025",
      "case_title": "CR. MISC./74818/2025 of Sumit Kumar Vs The State of Bihar",
      "decision_date": "10-11-2025",
      "decision_year": 2025,
      "download_time": "2025-11-11T07:29:14.804120",
      "download_duration_seconds": 7.16
    },
    {
      "success": true,
      "filename": "CR._MISC._75332_2025_of_Vikash_Kumar_Vs_The_State_of_Bihar_CNR_BRHC011107252025_1762846072520.pdf",
      "s3_key": "judgments/CR._MISC._75332_2025_of_Vikash_Kumar_Vs_The_State_of_Bihar_CNR_BRHC011107252025_1762846072520_31.pdf",
      "uploaded_to_s3": true,
      "cnr": "BRHC011107252025",
      "case_title": "CR. MISC./75332/2025 of Vikash Kumar Vs The State of Bihar",
      "decision_date": "10-11-2025",
      "decision_year": 2025,
      "download_time": "2025-11-11T07:29:24.558344",
      "download_duration_seconds": 7.15
    },
    {
      "success": true,
      "filename": "CR._MISC._71270_2025_of_Raj_Kumar_Rai_Vs_The_State_of_Bihar_CNR_BRHC011013872025_1762846072581.pdf",
      "s3_key": "judgments/CR._MISC._71270_2025_of_Raj_Kumar_Rai_Vs_The_State_of_Bihar_CNR_BRHC011013872025_1762846072581_31.pdf",
      "uploaded_to_s3": true,
      "cnr": "BRHC011013872025",
      "case_title": "CR. MISC./71270/2025 of Raj Kumar Rai Vs The State of Bihar",
      "decision_date": "10-11-2025",
      "decision_year": 2025,
      "download_time": "2025-11-11T07:29:34.635495",
      "download_duration_seconds": 7.49
    },
    {
      "success": true,
      "filename": "CR._MISC._73884_2025_of_Chandan_Kumar_@_Chandan_Jaiswal_@_Chandan_Gupta_Vs_The_State_of_Bihar_CNR_BRHC011079232025_1762846072676.pdf",
      "s3_key": "judgments/CR._MISC._73884_2025_of_Chandan_Kumar_@_Chandan_Jaiswal_@_Chandan_Gupta_Vs_The_State_of_Bihar_CNR_BRHC011079232025_1762846072676_31.pdf",
      "uploaded_to_s3": true,
      "cnr": "BRHC011079232025",
      "case_title": "CR. MISC./73884/2025 of Chandan Kumar @ Chandan Jaiswal @ Chandan Gupta Vs The State of Bihar",
      "decision_date": "10-11-2025",
      "decision_year": 2025,
      "download_time": "2025-11-11T07:29:44.516470",
      "download_duration_seconds": 7.22
    },
    {
      "success": true,
      "filename": "CR._MISC._75506_2025_of_Golu_Kumar_Vs_The_State_of_Bihar_CNR_BRHC011097202025_1762846072751.pdf",
      "s3_key": "judgments/CR._MISC._75506_2025_of_Golu_Kumar_Vs_The_State_of_Bihar_CNR_BRHC011097202025_1762846072751_31.pdf",
      "uploaded_to_s3": true,
      "cnr": "BRHC011097202025",
      "case_title": "CR. MISC./75506/2025 of Golu Kumar Vs The State of Bihar",
      "decision_date": "10-11-2025",
      "decision_year": 2025,
      "download_time": "2025-11-11T07:29:54.290628",
      "download_duration_seconds": 7.08
    },
    {
      "success": true,
      "filename": "CR._MISC._74262_2025_of_Shyam_Kumar_@_Shyam_Sundar_Sah_Vs_The_State_of_Bihar_CNR_BRHC011086622025_1762846072824.pdf",
      "s3_key": "judgments/CR._MISC._74262_2025_of_Shyam_Kumar_@_Shyam_Sundar_Sah_Vs_The_State_of_Bihar_CNR_BRHC011086622025_1762846072824_31.pdf",
      "uploaded_to_s3": true,
      "cnr": "BRHC011086622025",
      "case_title": "CR. MISC./74262/2025 of Shyam Kumar @ Shyam Sundar Sah Vs The State of Bihar",
      "decision_date": "10-11-2025",
      "decision_year": 2025,
      "download_time": "2025-11-11T07:30:03.987118",
      "download_duration_seconds": 7.07
    },
    {
      "success": true,
      "filename": "CR._MISC._74936_2025_of_Dharmendra_Rai_@_Mukhiya_@_Devendra_Rai_@_Davindra_Ray_Vs_The_State_of_Bihar_CNR_BRHC011095322025_1762846072901.pdf",
      "s3_key": "judgments/CR._MISC._74936_2025_of_Dharmendra_Rai_@_Mukhiya_@_Devendra_Rai_@_Davindra_Ray_Vs_The_State_of_Bihar_CNR_BRHC011095322025_1762846072901_31.pdf",
      "uploaded_to_s3": true,
      "cnr": "BRHC011095322025",
      "case_title": "CR. MISC./74936/2025 of Dharmendra Rai @ Mukhiya @ Devendra Rai @ Davindra Ray Vs The State of Bihar",
      "decision_date": "10-11-2025",
      "decision_year": 2025,
      "download_time": "2025-11-11T07:30:13.662113",
      "download_duration_seconds": 7.08
    },
    {
      "success": true,
      "filename": "CR._MISC._74436_2025_of_Rajmati_Devi_Vs_The_State_of_Bihar_CNR_BRHC011088092025_1762846072964.pdf",
      "s3_key": "judgments/CR._MISC._74436_2025_of_Rajmati_Devi_Vs_The_State_of_Bihar_CNR_BRHC011088092025_1762846072964_31.pdf",
      "uploaded_to_s3": true,
      "cnr": "BRHC011088092025",
      "case_title": "CR. MISC./74436/2025 of Rajmati Devi Vs The State of Bihar",
      "decision_date": "10-11-2025",
      "decision_year": 2025,
      "download_time": "2025-11-11T07:30:23.388840",
      "download_duration_seconds": 7.09
    },
    {
      "success": true,
      "filename": "WP_11534_2019_of_AMJAD_ILAHI_BHOKARE_Vs_STATE_OF_MAHARASHTRA_THROUGH_SECRETARY_SOCIAL_JUSTICE_DEPT._AND_ORS_CNR_HCBM070464402019_1762846073026.pdf",
      "s3_key": "judgments/WP_11534_2019_of_AMJAD_ILAHI_BHOKARE_Vs_STATE_OF_MAHARASHTRA_THROUGH_SECRETARY_SOCIAL_JUSTICE_DEPT._AND_ORS_CNR_HCBM070464402019_1762846073026_31.pdf",
      "uploaded_to_s3": true,
      "cnr": "HCBM070464402019",
      "case_title": "WP/11534/2019 of AMJAD ILAHI BHOKARE Vs STATE OF MAHARASHTRA THROUGH SECRETARY SOCIAL JUSTICE DEPT. AND ORS",
      "decision_date": "10-11-2025",
      "decision_year": 2025,
      "download_time": "2025-11-11T07:30:33.001143",
      "download_duration_seconds": 6.97
    },
    {
      "success": true,
      "filename": "WP_12914_2024_of_AKSHAY_ARVIND_PORE_Vs_ZILLA_PARISHAD_SANGLI_THR_THE_CEO_AND_ANR_CNR_HCBM070416652024_1762846073130.pdf",
      "s3_key": "judgments/WP_12914_2024_of_AKSHAY_ARVIND_PORE_Vs_ZILLA_PARISHAD_SANGLI_THR_THE_CEO_AND_ANR_CNR_HCBM070416652024_1762846073130_31.pdf",
      "uploaded_to_s3": true,
      "cnr": "HCBM070416652024",
      "case_title": "WP/12914/2024 of AKSHAY ARVIND PORE Vs ZILLA PARISHAD SANGLI THR THE CEO AND ANR",
      "decision_date": "10-11-2025",
      "decision_year": 2025,
      "download_time": "2025-11-11T07:30:42.686041",
      "download_duration_seconds": 7.0
    },
    {
      "success": true,
      "filename": "SCA_7858_2024_of_RAJAKBHAI_MAMADBHAI_JUNEJA_Vs_PACHIM_GUJARAT_VIJ_COMPANY_LIMITED_CNR_GJHC240314362024_1762846073184.pdf",
      "s3_key": "judgments/SCA_7858_2024_of_RAJAKBHAI_MAMADBHAI_JUNEJA_Vs_PACHIM_GUJARAT_VIJ_COMPANY_LIMITED_CNR_GJHC240314362024_1762846073184_31.pdf",
      "uploaded_to_s3": true,
      "cnr": "GJHC240314362024",
      "case_title": "SCA/7858/2024 of RAJAKBHAI MAMADBHAI JUNEJA Vs PACHIM GUJARAT VIJ COMPANY LIMITED",
      "decision_date": "10-11-2025",
      "decision_year": 2025,
      "download_time": "2025-11-11T07:30:52.466643",
      "download_duration_seconds": 7.14
    },
    {
      "success": true,
      "filename": "SCA_15074_2025_of_BHUPESH_NAUTAMLAL_YAGNIK_Vs_STATE_OF_GUJARAT_CNR_GJHC240761992025_1762846073252.pdf",
      "s3_key": "judgments/SCA_15074_2025_of_BHUPESH_NAUTAMLAL_YAGNIK_Vs_STATE_OF_GUJARAT_CNR_GJHC240761992025_1762846073252_31.pdf",
      "uploaded_to_s3": true,
      "cnr": "GJHC240761992025",
      "case_title": "SCA/15074/2025 of BHUPESH NAUTAMLAL YAGNIK Vs STATE OF GUJARAT",
      "decision_date": "10-11-2025",
      "decision_year": 2025,
      "download_time": "2025-11-11T07:31:02.299899",
      "download_duration_seconds": 7.24
    },
    {
      "success": true,
      "filename": "WP(C)_31615_2025_of_BHAVESH_PATEL_Vs_STATE_OF_ODISHA_CNR_ODHC010793522025_1762846073323.pdf",
      "s3_key": "judgments/WP(C)_31615_2025_of_BHAVESH_PATEL_Vs_STATE_OF_ODISHA_CNR_ODHC010793522025_1762846073323_31.pdf",
      "uploaded_to_s3": true,
      "cnr": "ODHC010793522025",
      "case_title": "WP(C)/31615/2025 of BHAVESH PATEL Vs STATE OF ODISHA",
      "decision_date": "10-11-2025",
      "decision_year": 2025,
      "download_time": "2025-11-11T07:31:12.531057",
      "download_duration_seconds": 7.64
    },
    {
      "success": true,
      "filename": "CMAPL_90_2025_of_SATISH_RAM_Vs_STATE_OF_ODISHA_CNR_ODHC010178382025_1762846073380.pdf",
      "s3_key": "judgments/CMAPL_90_2025_of_SATISH_RAM_Vs_STATE_OF_ODISHA_CNR_ODHC010178382025_1762846073380_31.pdf",
      "uploaded_to_s3": true,
      "cnr": "ODHC010178382025",
      "case_title": "CMAPL/90/2025 of SATISH RAM Vs STATE OF ODISHA",
      "decision_date": "10-11-2025",
      "decision_year": 2025,
      "download_time": "2025-11-11T07:31:23.330890",
      "download_duration_seconds": 8.18
    },
    {
      "success": true,
      "filename": "CMAP_269_2024_of_MAHESH_CHAND_S_O_SHRI_RAMCHANDER_Vs_DESHRAJ_MEENA_CNR_RJHC020754032024_1762846073446.pdf",
      "s3_key": "judgments/CMAP_269_2024_of_MAHESH_CHAND_S_O_SHRI_RAMCHANDER_Vs_DESHRAJ_MEENA_CNR_RJHC020754032024_1762846073446_31.pdf",
      "uploaded_to_s3": true,
      "cnr": "RJHC020754032024",
      "case_title": "CMAP/269/2024 of MAHESH CHAND S/O SHRI RAMCHANDER Vs DESHRAJ MEENA",
      "decision_date": "10-11-2025",
      "decision_year": 2025,
      "download_time": "2025-11-11T07:31:33.068274",
      "download_duration_seconds": 7.11
    },
    {
      "success": true,
      "filename": "CRMA_54_2024_of_PRASANNA_SUDHAKAR_SAMANT_Vs_ARUN_SHAH_AND_ANR_CNR_HCBM050009302024_1762846073533.pdf",
      "s3_key": "judgments/CRMA_54_2024_of_PRASANNA_SUDHAKAR_SAMANT_Vs_ARUN_SHAH_AND_ANR_CNR_HCBM050009302024_1762846073533_31.pdf",
      "uploaded_to_s3": true,
      "cnr": "HCBM050009302024",
      "case_title": "CRMA/54/2024 of PRASANNA SUDHAKAR SAMANT Vs ARUN SHAH AND ANR",
      "decision_date": "10-11-2025",
      "decision_year": 2025,
      "download_time": "2025-11-11T07:31:42.546833",
      "download_duration_seconds": 6.86
    },
    {
      "success": true,
      "filename": "CRM(M)_1667_2025_of_HARADEB_MAJHI_Vs_STATE_OF_WEST_BENGAL_CNR_WBCHCA0431622025_1762846073604.pdf",
      "s3_key": "judgments/CRM(M)_1667_2025_of_HARADEB_MAJHI_Vs_STATE_OF_WEST_BENGAL_CNR_WBCHCA0431622025_1762846073604_31.pdf",
      "uploaded_to_s3": true,
      "cnr": "WBCHCA0431622025",
      "case_title": "CRM(M)/1667/2025 of HARADEB MAJHI Vs STATE OF WEST BENGAL",
      "decision_date": "10-11-2025",
      "decision_year": 2025,
      "download_time": "2025-11-11T07:31:52.358953",
      "download_duration_seconds": 7.2
    },
    {
      "success": true,
      "filename": "CO_1701_2023_of_MESSERS_DIMPAL_PROPETIERS_PVT._LTD._Vs_RAM_KRISHNA_VIVEKANANDA_MISSION_CNR_WBCHCA0256442023_1762846073656.pdf",
      "s3_key": "judgments/CO_1701_2023_of_MESSERS_DIMPAL_PROPETIERS_PVT._LTD._Vs_RAM_KRISHNA_VIVEKANANDA_MISSION_CNR_WBCHCA0256442023_1762846073656_31.pdf",
      "uploaded_to_s3": true,
      "cnr": "WBCHCA0256442023",
      "case_title": "CO/1701/2023 of MESSERS DIMPAL PROPETIERS PVT. LTD. Vs RAM KRISHNA VIVEKANANDA MISSION",
      "decision_date": "10-11-2025",
      "decision_year": 2025,
      "download_time": "2025-11-11T07:32:03.129465",
      "download_duration_seconds": 8.17
    }
  ]
}